password_generator/__init__.py
password_generator/generator.py
oceanmaster_password_generator-0.1.0.dist-info/METADATA
oceanmaster_password_generator-0.1.0.dist-info/WHEEL
oceanmaster_password_generator-0.1.0.dist-info/top_level.txt
oceanmaster_password_generator-0.1.0.dist-info/RECORD
