Metadata-Version: 2.4
Name: oceanmaster-password-generator
Version: 0.1.0
Summary: An advanced password generator library with multiple security features
Author: Abhishek Kumar / ocean-masterO
Classifier: Programming Language :: Python :: 3
Classifier: License :: OSI Approved :: MIT License
Classifier: Operating System :: OS Independent
Requires-Python: >=3.6
Dynamic: author
Dynamic: classifier
Dynamic: requires-python
Dynamic: summary
